trading_sdk/__init__.py
trading_sdk/__init__.pyi
trading_sdk/util.py
trading_sdk/market/__init__.py
trading_sdk/market/market_data/__init__.py
trading_sdk/market/market_data/candles.py
trading_sdk/market/market_data/depth.py
trading_sdk/market/market_data/funding_rate_history.py
trading_sdk/market/market_data/info.py
trading_sdk/market/market_data/time.py
trading_sdk/market/market_data/trades.py
trading_sdk/market/market_streams/__init__.py
trading_sdk/market/market_streams/depth.py
trading_sdk/market/market_streams/trades.py
trading_sdk/market/trading/__init__.py
trading_sdk/market/trading/cancel_order.py
trading_sdk/market/trading/open_orders.py
trading_sdk/market/trading/place_order.py
trading_sdk/market/trading/query_order.py
trading_sdk/market/types/__init__.py
trading_sdk/market/types/__init__.pyi
trading_sdk/market/types/order.py
trading_sdk/market/user_data/__init__.py
trading_sdk/market/user_data/balances.py
trading_sdk/market/user_data/my_funding_history.py
trading_sdk/market/user_data/my_trades.py
trading_sdk/market/user_data/positions.py
trading_sdk/market/user_streams/__init__.py
trading_sdk/market/user_streams/my_trades.py
trading_sdk/reporting/__init__.py
trading_sdk/reporting/report.py
trading_sdk/reporting/types.py
trading_sdk/types/__init__.py
trading_sdk/types/__init__.pyi
trading_sdk/types/exc.py
trading_sdk/types/misc.py
trading_sdk/types/networks.py
trading_sdk/wallet/__init__.py
trading_sdk/wallet/deposit_address.py
trading_sdk/wallet/deposit_history.py
trading_sdk/wallet/withdraw.py
trading_sdk/wallet/withdrawal_history.py
trading_sdk/wallet/withdrawal_methods.py
trading_sdk-0.2.1.dist-info/METADATA
trading_sdk-0.2.1.dist-info/WHEEL
trading_sdk-0.2.1.dist-info/top_level.txt
trading_sdk-0.2.1.dist-info/RECORD
