Metadata-Version: 2.4
Name: trading-sdk
Version: 0.2.1
Summary: An abstract, fully-typed, async Python SDK for automated crypto trading. By Tribulnation.
Author-email: Marcel Claramunt <marcel@tribulnation.com>
Project-URL: Github, https://github.com/tribulnation/sdk.git
Requires-Python: >=3.10
Requires-Dist: lazy-loader
